django_taggit_helpers-0.1.4.dist-info/DESCRIPTION.rst
django_taggit_helpers-0.1.4.dist-info/METADATA
django_taggit_helpers-0.1.4.dist-info/metadata.json
django_taggit_helpers-0.1.4.dist-info/RECORD
django_taggit_helpers-0.1.4.dist-info/top_level.txt
django_taggit_helpers-0.1.4.dist-info/WHEEL
taggit_helpers/__init__.py
taggit_helpers/admin.py
taggit_helpers/apps.py
