Metadata-Version: 2.0
Name: django-taggit-helpers
Version: 0.1.4
Summary: Django admin helper classes for django-taggit tags
Home-page: https://github.com/mfcovington/django-taggit-helpers
Author: Michael F. Covington
Author-email: mfcovington@gmail.com
License: BSD License
Keywords: tags tagging taggit django-taggit
Platform: UNKNOWN
Classifier: Development Status :: 3 - Alpha
Classifier: Environment :: Web Environment
Classifier: Framework :: Django
Classifier: Framework :: Django :: 1.7
Classifier: Framework :: Django :: 1.8
Classifier: Framework :: Django :: 1.9
Classifier: Intended Audience :: Developers
Classifier: License :: OSI Approved :: BSD License
Classifier: Operating System :: OS Independent
Classifier: Programming Language :: Python
Classifier: Programming Language :: Python :: 2
Classifier: Programming Language :: Python :: 2.7
Classifier: Programming Language :: Python :: 3
Classifier: Programming Language :: Python :: 3.2
Classifier: Programming Language :: Python :: 3.3
Classifier: Programming Language :: Python :: 3.4
Requires-Dist: django (>=1.7)
Requires-Dist: django-taggit (>=0.12.0)
